zenforge/__init__.py
zenforge/cli/__init__.py
zenforge/cli/codes.py
zenforge/cli/display.py
zenforge/cli/message.py
zenforge/config/__init__.py
zenforge/config/deps.py
zenforge/config/toml.py
zenforge/create/__init__.py
zenforge/create/method.py
zenforge/main.py
zenforge/template/root/.flake8
zenforge/template/root/.gitignore
zenforge/template/root/README.md
zenforge-0.1.3.dist-info/LICENSE
zenforge-0.1.3.dist-info/METADATA
zenforge-0.1.3.dist-info/WHEEL
zenforge-0.1.3.dist-info/entry_points.txt
zenforge-0.1.3.dist-info/RECORD
