Metadata-Version: 2.3
Name: zenforge
Version: 0.1.3
Summary: A simple CLI tool for bootstrapping new projects fast
License: Apache-2.0
Keywords: python,project-bootstrapping,cli-tool
Author: Ryan Partridge
Author-email: rpartridge101@gmail.com
Maintainer: Ryan Partridge
Maintainer-email: rpartridge101@gmail.com
Requires-Python: >=3.12,<4.0
Classifier: Development Status :: 3 - Alpha
Classifier: Environment :: Console
Classifier: Programming Language :: Python
Classifier: Programming Language :: Python :: 3
Classifier: Natural Language :: English
Classifier: Operating System :: Microsoft :: Windows
Classifier: Operating System :: MacOS
Classifier: Operating System :: POSIX :: Linux
Classifier: Framework :: FastAPI
Classifier: Framework :: Pydantic
Classifier: Intended Audience :: Developers
Classifier: License :: OSI Approved :: Apache Software License
Classifier: Topic :: Scientific/Engineering :: Artificial Intelligence
Classifier: Topic :: Software Development :: Build Tools
Requires-Dist: questionary (>=2.1.0,<3.0.0)
Requires-Dist: typer (>=0.15.1,<0.16.0)
Project-URL: homepage, https://github.com/Achronus/zenforge
Project-URL: issues, https://github.com/Achronus/zenforge/issues
Project-URL: repository, https://github.com/Achronus/zenforge
